pytest_pythonhashseed/__init__.py
pytest_pythonhashseed-2.0.1.dist-info/entry_points.txt
pytest_pythonhashseed-2.0.1.dist-info/licenses/LICENSE
pytest_pythonhashseed-2.0.1.dist-info/WHEEL
pytest_pythonhashseed-2.0.1.dist-info/METADATA
pytest_pythonhashseed-2.0.1.dist-info/RECORD
