Metadata-Version: 2.4
Name: pytest-pythonhashseed
Version: 2.0.1
Summary: Pytest plugin to set PYTHONHASHSEED env var.
Keywords: env,envvars,pytest,pythonhashseed,testing
Author-email: Michael Samoglyadov <mixas.sr@gmail.com>
Requires-Python: >=3.6
Classifier: Development Status :: 4 - Beta
Classifier: Framework :: Pytest
Classifier: Intended Audience :: Developers
Classifier: License :: OSI Approved :: Apache Software License
Classifier: Operating System :: OS Independent
Classifier: Programming Language :: Python :: 3 :: Only
Classifier: Topic :: Software Development :: Quality Assurance
Classifier: Topic :: Software Development :: Testing
License-File: LICENSE
Requires-Dist: pytest>=3.0.0
Requires-Dist: pytest ; extra == "test"
Requires-Dist: pytest-cov ; extra == "test"
Requires-Dist: pytest-ruff ; extra == "test"
Requires-Dist: ruff ; extra == "test"
Project-URL: Homepage, https://github.com/mr-mixas/pytest-pythonhashseed
Project-URL: Repository, https://github.com/mr-mixas/pytest-pythonhashseed.git
Provides-Extra: test
